nikki/__init__.py
nikki/cli.py
nikki/nikki.py
nikki-0.0.4.dist-info/METADATA
nikki-0.0.4.dist-info/RECORD
nikki-0.0.4.dist-info/WHEEL
nikki-0.0.4.dist-info/entry_points.txt
nikki-0.0.4.dist-info/top_level.txt
