Metadata-Version: 2.1
Name: nikki
Version: 0.0.4
Summary: Simple crypted journal for personal use
Home-page: https://github.com/WIN32GG/nikki
Author: win32gg
Author-email: gregor.jouet@laposte.net
License: MIT
Platform: UNKNOWN
Requires-Python: >=3.4, <4
Requires-Dist: splogger
Requires-Dist: python-gnupg
Requires-Dist: click
Requires-Dist: click-completion
